mcp_server_nhentai/__init__.py
mcp_server_nhentai/__main__.py
mcp_server_nhentai/server.py
mcp_server_nhentai-0.1.1.dist-info/METADATA
mcp_server_nhentai-0.1.1.dist-info/WHEEL
mcp_server_nhentai-0.1.1.dist-info/entry_points.txt
mcp_server_nhentai-0.1.1.dist-info/RECORD
