Metadata-Version: 2.4
Name: mcp-server-nhentai
Version: 0.1.1
Summary: A MCP server for nhentai Dou Shu chart generation
Author-email: UnieAI Eric <chouwei88929@gmail.com>
Classifier: Development Status :: 4 - Beta
Classifier: Intended Audience :: Developers
Classifier: License :: OSI Approved :: MIT License
Classifier: Programming Language :: Python :: 3
Classifier: Programming Language :: Python :: 3.10
Requires-Python: >=3.10
Requires-Dist: beautifulsoup4>=4.12.3
Requires-Dist: mcp>=1.0.0
Requires-Dist: playwright>=1.43.0
Requires-Dist: pydantic>=2.0.0
Requires-Dist: tzdata>=2024.2
